evalsense/__init__.py
evalsense/constants.py
evalsense/logging.py
evalsense/py.typed
evalsense/cli/__init__.py
evalsense/cli/__main__.py
evalsense/cli/main.py
evalsense/dataset_config/ACI-BENCH.yml
evalsense/datasets/__init__.py
evalsense/datasets/dataset_config.py
evalsense/datasets/dataset_manager.py
evalsense/datasets/managers/__init__.py
evalsense/datasets/managers/aci_bench.py
evalsense/datasets/managers/huggingface.py
evalsense/evaluation/__init__.py
evalsense/evaluation/evaluator.py
evalsense/evaluation/experiment.py
evalsense/evaluation/evaluators/__init__.py
evalsense/evaluation/evaluators/bertscore.py
evalsense/evaluation/evaluators/bleu.py
evalsense/evaluation/evaluators/g_eval.py
evalsense/evaluation/evaluators/qags.py
evalsense/evaluation/evaluators/rouge.py
evalsense/generation/__init__.py
evalsense/generation/generation_steps.py
evalsense/generation/model_config.py
evalsense/tasks/__init__.py
evalsense/tasks/task_preprocessor.py
evalsense/utils/__init__.py
evalsense/utils/dict.py
evalsense/utils/files.py
evalsense/utils/huggingface.py
evalsense/utils/records.py
evalsense/utils/text.py
evalsense/webui/__init__.py
evalsense/webui/app.py
evalsense/webui/execution.py
evalsense/webui/state.py
evalsense/webui/utils.py
evalsense/webui/components/__init__.py
evalsense/webui/components/data.py
evalsense/webui/components/evaluators.py
evalsense/webui/components/execution.py
evalsense/webui/components/generation.py
evalsense/webui/components/models.py
evalsense/webui/components/results.py
evalsense/webui/configurators/__init__.py
evalsense/webui/configurators/evaluator_configurator.py
evalsense/webui/configurators/evaluators/__init__.py
evalsense/webui/configurators/evaluators/bertscore.py
evalsense/webui/configurators/evaluators/bleu.py
evalsense/webui/configurators/evaluators/g_eval.py
evalsense/webui/configurators/evaluators/rouge.py
evalsense/workflow/__init__.py
evalsense/workflow/pipeline.py
evalsense/workflow/project.py
evalsense-0.1.5.dist-info/METADATA
evalsense-0.1.5.dist-info/WHEEL
evalsense-0.1.5.dist-info/entry_points.txt
evalsense-0.1.5.dist-info/licenses/LICENCE
evalsense-0.1.5.dist-info/RECORD
