Metadata-Version: 2.4
Name: evalsense
Version: 0.1.5
Summary: Tools for evaluating large language models.
Project-URL: Homepage, https://github.com/nhsengland/evalsense
Project-URL: Issues, https://github.com/nhsengland/evalsense/issues
Author-email: Adam Dejl <adam.dejl18@imperial.ac.uk>
License-Expression: MIT
License-File: LICENCE
Keywords: Artificial Intelligence,LLM Benchmarking,LLM Evaluation,LLMs,Large Language Models,Machine Learning
Classifier: Development Status :: 3 - Alpha
Classifier: Intended Audience :: Developers
Classifier: Intended Audience :: Science/Research
Classifier: License :: OSI Approved :: MIT License
Classifier: Operating System :: OS Independent
Classifier: Programming Language :: Python :: 3
Classifier: Topic :: Scientific/Engineering :: Artificial Intelligence
Requires-Python: >=3.12
Requires-Dist: datasets>=3.2.0
Requires-Dist: evaluate>=0.4.3
Requires-Dist: inspect-ai>=0.3.87
Requires-Dist: matplotlib>=3.10.0
Requires-Dist: numpy<2.0.0
Requires-Dist: openai>=1.65.3
Requires-Dist: pandas>=2.2.3
Requires-Dist: platformdirs>=4.3.6
Requires-Dist: polars>=1.22.0
Requires-Dist: pydantic>=2.10.6
Requires-Dist: pyyaml>=6.0.2
Requires-Dist: rouge-score>=0.1.2
Requires-Dist: scipy>=1.15.3
Requires-Dist: seaborn>=0.13.2
Requires-Dist: tenacity>=9.0.0
Requires-Dist: tqdm>=4.67.1
Requires-Dist: typer>=0.15.1
Provides-Extra: all
Requires-Dist: bert-score>=0.3.13; extra == 'all'
Requires-Dist: gradio>=5.44.1; extra == 'all'
Requires-Dist: ipywidgets>=8.1.5; extra == 'all'
Requires-Dist: jupyterlab>=4.3.5; extra == 'all'
Requires-Dist: torch>=2.6; extra == 'all'
Requires-Dist: transformers>=4.50.0; extra == 'all'
Requires-Dist: vllm>=0.8.2; extra == 'all'
Provides-Extra: interactive
Requires-Dist: gradio>=5.44.1; extra == 'interactive'
Requires-Dist: ipywidgets>=8.1.5; extra == 'interactive'
Requires-Dist: jupyterlab>=4.3.5; extra == 'interactive'
Provides-Extra: jupyter
Requires-Dist: ipywidgets>=8.1.5; extra == 'jupyter'
Requires-Dist: jupyterlab>=4.3.5; extra == 'jupyter'
Provides-Extra: local
Requires-Dist: bert-score>=0.3.13; extra == 'local'
Requires-Dist: torch>=2.6; extra == 'local'
Requires-Dist: transformers>=4.50.0; extra == 'local'
Requires-Dist: vllm>=0.8.2; extra == 'local'
Provides-Extra: transformers
Requires-Dist: bert-score>=0.3.13; extra == 'transformers'
Requires-Dist: torch>=2.6; extra == 'transformers'
Requires-Dist: transformers>=4.50.0; extra == 'transformers'
Provides-Extra: vllm
Requires-Dist: vllm>=0.8.2; extra == 'vllm'
Provides-Extra: webui
Requires-Dist: gradio>=5.44.1; extra == 'webui'
